osm_shortlink-1.4.1.dist-info/METADATA
osm_shortlink-1.4.1.dist-info/WHEEL
osm_shortlink/__init__.py
osm_shortlink/_lib.cp313t-win_amd64.pyd
osm_shortlink/_lib.pyi
osm_shortlink/py.typed
osm_shortlink-1.4.1.dist-info/RECORD
